crawler_utils/__init__.py
crawler_utils/captcha_detection/__init__.py
crawler_utils/captcha_detection/captcha_detection.py
crawler_utils/cloudflare_captcha_bypass.py
crawler_utils/credentials/__init__.py
crawler_utils/credentials/credential.py
crawler_utils/credentials/manager.py
crawler_utils/credentials/store/__init__.py
crawler_utils/credentials/store/local.py
crawler_utils/credentials/store/talisman.py
crawler_utils/deploy/__init__.py
crawler_utils/deploy/bump_version.py
crawler_utils/deploy/create_egg.py
crawler_utils/deploy/make_arguments_md_file.py
crawler_utils/domains.py
crawler_utils/echo.py
crawler_utils/files.py
crawler_utils/images.py
crawler_utils/kafka.py
crawler_utils/logstash.py
crawler_utils/metrics/__init__.py
crawler_utils/metrics/focus.py
crawler_utils/metrics/timer.py
crawler_utils/misc.py
crawler_utils/mongodb.py
crawler_utils/opensearch/__init__.py
crawler_utils/opensearch/dupefilter.py
crawler_utils/opensearch/dupefilter_strategies/__init__.py
crawler_utils/opensearch/dupefilter_strategies/delta_fetch_items.py
crawler_utils/opensearch/dupefilter_strategies/depth_based.py
crawler_utils/opensearch/dupefilter_strategies/drop_unproductive_requests.py
crawler_utils/opensearch/items_pipeline.py
crawler_utils/opensearch/request_fingerprint.py
crawler_utils/opensearch/requests_middleware.py
crawler_utils/opensearch/storage.py
crawler_utils/proxypy.py
crawler_utils/rabbitmq/__init__.py
crawler_utils/rabbitmq/rabbitmq_extension.py
crawler_utils/rabbitmq/rabbitmq_pipeline.py
crawler_utils/rabbitmq/schemas.py
crawler_utils/rabbitmq/utils.py
crawler_utils/sentry_logging/__init__.py
crawler_utils/sentry_logging/sentry_logging.py
crawler_utils/social_media/__init__.py
crawler_utils/social_media/items.py
crawler_utils/socks.py
crawler_utils/splash_proxy.py
crawler_utils/states/__init__.py
crawler_utils/states/local_store.py
crawler_utils/states/talisman_states_api.py
crawler_utils/talisman_controller.py
crawler_utils/talisman_job_env.py
modis_crawler_utils-0.3.48.dist-info/METADATA
modis_crawler_utils-0.3.48.dist-info/WHEEL
modis_crawler_utils-0.3.48.dist-info/entry_points.txt
modis_crawler_utils-0.3.48.dist-info/RECORD
