Metadata-Version: 2.3
Name: modis-crawler-utils
Version: 0.3.48
Summary: Scrapy utils for Modis crawlers projects.
License: BSD
Author: Varlamov
Author-email: varlamov@ispras.ru
Requires-Python: >=3.9,<4.0
Classifier: Development Status :: 3 - Alpha
Classifier: Framework :: Scrapy
Classifier: Intended Audience :: Developers
Classifier: License :: OSI Approved :: BSD License
Classifier: License :: Other/Proprietary License
Classifier: Operating System :: OS Independent
Classifier: Programming Language :: Python :: 3
Classifier: Programming Language :: Python :: 3.9
Classifier: Programming Language :: Python :: 3.10
Classifier: Programming Language :: Python :: 3.11
Classifier: Programming Language :: Python :: 3.12
Classifier: Programming Language :: Python :: 3.13
Requires-Dist: Pillow (>=7.1.2)
Requires-Dist: certifi
Requires-Dist: dateparser (>=1.2.0)
Requires-Dist: ephemeral-port-reserve (>=1.1.1)
Requires-Dist: itemadapter (>=0.2.0)
Requires-Dist: kafka-python-ng (>=2.2.3,<3.0.0)
Requires-Dist: opensearch-py (>=2.7.1,<3.0.0)
Requires-Dist: pika (>=1.3.2,<2.0.0)
Requires-Dist: pydantic (>=2.4.2,<3.0.0)
Requires-Dist: pymongo (>=3.10.1)
Requires-Dist: pytest (>=8.3.4,<9.0.0)
Requires-Dist: pytest-cases (>=3.8.6,<4.0.0)
Requires-Dist: pytest-check (>=2.5.0,<3.0.0)
Requires-Dist: pytest-dependency (>=0.6.0,<0.7.0)
Requires-Dist: python-logstash (>=0.4.6)
Requires-Dist: requests (>=2.23.0)
Requires-Dist: scrapy (>=2.6.0)
Requires-Dist: scrapy-puppeteer-client (>=0.0.6)
Requires-Dist: scrapy-splash (>=0.8.0)
Requires-Dist: sentry-sdk (>=2.13.0,<3.0.0)
Requires-Dist: twisted
Requires-Dist: uuid6 (>=2025.0.1,<2026.0.0)
Project-URL: Homepage, https://gitlab.at.ispras.ru/crawlers/crawler-utils
Project-URL: Repository, https://gitlab.at.ispras.ru/crawlers/crawler-utils
